Workbook

Sheet Cover
B2: STARBUCKS CORPORATION
B3: Three-Year Financial Forecast Model (FY2026E – FY2028E)
B4: Prepared for: Commercial Banking Internship Application Portfolio
B5: Base year: FY2025 (ended 9/28/2025) | All figures in $ millions unless noted
B8: Model Structure
B9: 1. Assumptions — Growth, margin, working capital, and financing drivers — all editable blue inputs
B10: 2. Income Statement — FY2024A–FY2025A actuals and FY2026E–FY2028E projected income statement
B11: 3. Cash Flow & Balance — Free cash flow build, working capital, debt, dividends, and cash roll-forward
B12: 4. Sensitivity Analysis — FY2028E free cash flow and net income under alternative growth/margin scenarios
B13: 5. Dashboard — Summary KPIs and charts
B15: Color Key
B16: Blue text — Hardcoded input / assumption — change these to run new scenarios
... B21: Source: Starbucks Corporation FY2025 Form 10-K and Q4/FY2025 earnings release (SEC EDGAR), fiscal year ended 9/28/2025.

Sheet Assumptions
A1: MODEL ASSUMPTIONS
A3: Driver | B3: FY2025A | C3: FY2026E | D3: FY2027E | E3: FY2028E
A5: Revenue & Margin Assumptions
A6: Revenue growth rate (YoY) | B6: ='Income Statement'!C6 -> 0.027869152 | C6: 0.03 | D6: 0.045 | E6: 0.055
A7: Product & distribution costs (% of revenue) | B7: ='Income Statement'!C7/'Income Statement'!C5 -> 0.31352395 | C7: 0.313 | D7: 0.312 | E7: 0.311
A8: Store operating expenses (% of revenue) | B8: ='Income Statement'!C8/'Income Statement'!C5 -> 0.45876497 | C8: 0.455 | D8: 0.448 | E8: 0.44
A9: Other operating expenses (% of revenue) | B9: ='Income Statement'!C9/'Income Statement'!C5 -> 0.015721647 | C9: 0.016 | D9: 0.016 | E9: 0.016
A10: General & administrative (% of revenue) | B10: ='Income Statement'!C11/'Income Statement'!C5 -> 0.070384355 | C10: 0.069 | D10: 0.067 | E10: 0.065
A11: Depreciation & amortization (% of revenue) | B11: ='Income Statement'!C10/'Income Statement'!C5 -> 0.045306634 | C11: 0.046 | D11: 0.046 | E11: 0.046
A12: Effective tax rate | B12: ='Income Statement'!C19/'Income Statement'!C18 -> 0.25948231 | C12: 0.255 | D12: 0.255 | E12: 0.255
A14: Capital, Working Capital & Financing Assumptions
A15: Capital expenditures (% of revenue) | B15: =2305.5/'Income Statement'!C5 -> 0.062001807 | C15: 0.06 | D15: 0.058 | E15: 0.055
A16: Accounts receivable (% of revenue) | B16: =1277.5/'Income Statement'!C5 -> 0.034355805 | C16: 0.034 | D16: 0.034 | E16: 0.034
A17: Inventory (% of revenue) | B17: =2185.6/'Income Statement'!C5 -> 0.058777337 | C17: 0.059 | D17: 0.059 | E17: 0.059
A18: Accounts payable (% of revenue) | B18: =1852.8/'Income Statement'!C5 -> 0.049827347 | C18: 0.05 | D18: 0.05 | E18: 0.05
A19: Effective interest rate on debt | B19: =429.3/16074.8 -> 0.026706398 | C19: 0.028 | D19: 0.028 | E19: 0.028
A20: Dividend growth rate (YoY) | B20: =2771.4/2585-1 -> 0.072108317 | C20: 0.07 | D20: 0.07 | E20: 0.07
A22: New term loan proceeds, FY2026E ($mm) | C22: 500 | D22: 0 | E22: 0
A24: Note: FY2025A column shows the actual historical ratio (computed via formula from the Income Statement tab) for comparison against forward assumptions.

Sheet Income Statement
A1: CONSOLIDATED INCOME STATEMENT ($ in millions)
A3: Line Item | B3: FY2024A | C3: FY2025A | D3: FY2026E | E3: FY2027E | F3: FY2028E
A5: Total net revenues | B5: 36176.2 | C5: 37184.4 | D5: =C5*(1+Assumptions!C6) -> 38299.932 | E5: =D5*(1+Assumptions!D6) -> 40023.429 | F5: =E5*(1+Assumptions!E6) -> 42224.718
A6: Revenue growth % | C6: =C5/B5-1 -> 0.027869152 | D6: =D5/C5-1 -> 0.03 | E6: =E5/D5-1 -> 0.045 | F6: =F5/E5-1 -> 0.055
A7: Product & distribution costs | B7: 11180.6 | C7: 11658.2 | D7: =D5*Assumptions!C7 -> 11987.879 | E7: =E5*Assumptions!D7 -> 12487.31 | F7: =F5*Assumptions!E7 -> 13131.887
A8: Store operating expenses | B8: 15286.5 | C8: 17058.9 | D8: =D5*Assumptions!C8 -> 17426.469 | E8: =E5*Assumptions!D8 -> 17930.496 | F8: =F5*Assumptions!E8 -> 18578.876
A9: Other operating expenses | B9: 565.6 | C9: 584.6 | D9: =D5*Assumptions!C9 -> 612.79891 | E9: =E5*Assumptions!D9 -> 640.37486 | F9: =F5*Assumptions!E9 -> 675.59548
A10: Depreciation & amortization | B10: 1512.6 | C10: 1684.7 | D10: =D5*Assumptions!C11 -> 1761.7969 | E10: =E5*Assumptions!D11 -> 1841.0777 | F10: =F5*Assumptions!E11 -> 1942.337
A11: General & administrative expenses | B11: 2523.3 | C11: 2617.2 | D11: =D5*Assumptions!C10 -> 2642.6953 | E11: =E5*Assumptions!D10 -> 2681.5697 | F11: =F5*Assumptions!E10 -> 2744.6066
A12: Restructuring & impairments (one-time) | B12: 0 | C12: 892 | D12: 0 | E12: 0 | F12: 0
A13: Total operating expenses | B13: =SUM(B7:B12) -> 31068.6 | C13: =SUM(C7:C12) -> 34495.6 | D13: =SUM(D7:D12) -> 34431.639 | E13: =SUM(E7:E12) -> 35580.828 | F13: =SUM(F7:F12) -> 37073.302
A14: Income from equity investees | B14: 301.2 | C14: 247.8 | D14: 247.8 | E14: 247.8 | F14: 247.8
A15: Operating income (EBIT) | B15: =B5-B13+B14 -> 5408.8 | C15: =C5-C13+C14 -> 2936.6 | D15: =D5-D13+D14 -> 4116.0931 | E15: =E5-E13+E14 -> 4690.4006 | F15: =F5-F13+F14 -> 5399.2155
A16: Operating margin % | B16: =B15/B5 -> 0.14951266 | C16: =C15/C5 -> 0.078973978 | D16: =D15/D5 -> 0.10746999 | E16: =E15/E5 -> 0.11719137 | F16: =F15/F5 -> 0.1278686
A17: Interest expense, net | B17: 439.2 | C17: 429.3 | D17: ='Cash Flow & Balance'!D28*Assumptions!C19 -> 450.0944 | E17: ='Cash Flow & Balance'!E28*Assumptions!D19 -> 464.0944 | F17: ='Cash Flow & Balance'!F28*Assumptions!E19 -> 464.0944
A18: Earnings before income taxes | B18: =B15-B17 -> 4969.6 | C18: =C15-C17 -> 2507.3 | D18: =D15-D17 -> 3665.9987 | E18: =E15-E17 -> 4226.3062 | F18: =F15-F17 -> 4935.1211
A19: Income tax expense | B19: 1207.3 | C19: 650.6 | D19: =D18*Assumptions!C12 -> 934.82968 | E19: =E18*Assumptions!D12 -> 1077.7081 | F19: =F18*Assumptions!E12 -> 1258.4559
A20: Net earnings attributable to SBUX | B20: =B18-B19 -> 3762.3 | C20: =C18-C19 -> 1856.7 | D20: =D18-D19 -> 2731.1691 | E20: =E18-E19 -> 3148.5981 | F20: =F18-F19 -> 3676.6652
A21: Net margin % | B21: =B20/B5 -> 0.10399931 | C21: =C20/C5 -> 0.04993223 | D21: =D20/D5 -> 0.071310024 | E21: =E20/E5 -> 0.078668875 | F21: =F20/F5 -> 0.087073768

Sheet Cash Flow & Balance
A1: CASH FLOW BUILD, WORKING CAPITAL & DEBT SCHEDULE ($ in millions)
A3: Line Item | B3: FY2024A | C3: FY2025A | D3: FY2026E | E3: FY2027E | F3: FY2028E
A5: Free Cash Flow Build
A6: Net income | B6: ='Income Statement'!B20 -> 3762.3 | C6: ='Income Statement'!C20 -> 1856.7 | D6: ='Income Statement'!D20 -> 2731.1691 | E6: ='Income Statement'!E20 -> 3148.5981 | F6: ='Income Statement'!F20 -> 3676.6652
A7: + Depreciation & amortization | B7: ='Income Statement'!B10 -> 1512.6 | C7: ='Income Statement'!C10 -> 1684.7 | D7: ='Income Statement'!D10 -> 1761.7969 | E7: ='Income Statement'!E10 -> 1841.0777 | F7: ='Income Statement'!F10 -> 1942.337
A8: – Increase in net working capital | C8: =C24-B24 -> 214.7 | D8: =D24-C24 -> 36.597076 | E8: =E24-D24 -> 74.110368 | F8: =F24-E24 -> 94.655409
A9: Cash flow from operations | B9: 6095.6 | C9: 4747.5 | D9: =D6+D7-D8 -> 4456.3689 | E9: =E6+E7-E8 -> 4915.5655 | F9: =F6+F7-F8 -> 5524.3468
A10: Free Cash Flow
A11: – Capital expenditures | B11: 2333.6 | C11: 2305.5 | D11: ='Income Statement'!D5*Assumptions!C15 -> 2297.9959 | E11: ='Income Statement'!E5*Assumptions!D15 -> 2321.3589 | F11: ='Income Statement'!F5*Assumptions!E15 -> 2322.3595
A12: — Free cash flow | B12: =B9-B11 -> 3762 | C12: =C9-C11 -> 2442 | D12: =D9-D11 -> 2158.3729 | E12: =E9-E11 -> 2594.2066 | F12: =F9-F11 -> 3201.9874
A13: Financing & Cash Roll-Forward
A14: + New term loan proceeds | C14: 0 | D14: =Assumptions!C22 -> 500 | E14: =Assumptions!D22 -> 0 | F14: =Assumptions!E22 -> 0
A15: – Dividends paid | B15: 2585 | C15: 2771.4 | D15: =C15*(1+Assumptions!C20) -> 2965.398 | E15: =D15*(1+Assumptions!D20) -> 3172.9759 | F15: =E15*(1+Assumptions!E20) -> 3395.0842
A16: — Net change in cash | C16: =C12+C14-C15 -> -329.4 | D16: =D12+D14-D15 -> -307.02507 | E16: =E12+E14-E15 -> -578.76925 | F16: =F12+F14-F15 -> -193.09679
A17: Beginning cash balance | C17: 3286.2 | D17: =C18 -> 3219.8 | E17: =D18 -> 2912.7749 | F17: =E18 -> 2334.0057
A18: Ending cash balance | C18: 3219.8 | D18: =D17+D16 -> 2912.7749 | E18: =E17+E16 -> 2334.0057 | F18: =F17+F16 -> 2140.9089
A20: Working Capital Detail
A21: Accounts receivable | B21: 1213.8 | C21: 1277.5 | D21: ='Income Statement'!D5*Assumptions!C16 -> 1302.1977 | E21: ='Income Statement'!E5*Assumptions!D16 -> 1360.7966 | F21: ='Income Statement'!F5*Assumptions!E16 -> 1435.6404
A22: Inventory | B22: 1777.3 | C22: 2185.6 | D22: ='Income Statement'!D5*Assumptions!C17 -> 2259.696 | E22: ='Income Statement'!E5*Assumptions!D17 -> 2361.3823 | F22: ='Income Statement'!F5*Assumptions!E17 -> 2491.2583
A23: Accounts payable | B23: 1595.5 | C23: 1852.8 | D23: ='Income Statement'!D5*Assumptions!C18 -> 1914.9966 | E23: ='Income Statement'!E5*Assumptions!D18 -> 2001.1714 | F23: ='Income Statement'!F5*Assumptions!E18 -> 2111.2359
A24: Net working capital (AR + Inv – AP) | B24: =B21+B22-B23 -> 1395.6 | C24: =C21+C22-C23 -> 1610.3 | D24: =D21+D22-D23 -> 1646.8971 | E24: =E21+E22-E23 -> 1721.0074 | F24: =F21+F22-F23 -> 1815.6629
A26: Debt Schedule
A28: Beginning total debt | C28: 15568.4 | D28: =C30 -> 16074.8 | E28: =D30 -> 16574.8 | F28: =E30 -> 16574.8
A29: + New borrowings, net | C29: 506.4 | D29: =Assumptions!C22 -> 500 | E29: =Assumptions!D22 -> 0 | F29: =Assumptions!E22 -> 0
A30: Ending total debt | C30: 16074.8 | D30: =D28+D29 -> 16574.8 | E30: =E28+E29 -> 16574.8 | F30: =F28+F29 -> 16574.8
A32: Note: Operating cash flow here is a simplified proxy (net income + D&A – ΔNWC) for forecasting purposes; it will not tie exactly to GAAP operating cash flow, which also reflects stock-based comp, deferred taxes, and other non-cash items.

Sheet Sensitivity Analysis
A1: FY2028E SENSITIVITY ANALYSIS — FREE CASH FLOW ($mm)
A2: Two-way sensitivity: flat annual revenue growth rate (columns) vs. flat store operating expense ratio (rows), compounded over 3 years from the FY2025A base.
A4: Fixed assumptions used (from Assumptions tab): product & distribution cost %, other opex %, G&A %, D&A %, tax rate, capex %, and interest expense held at FY2028E levels.
A6: FCF sensitivity: growth (cols) × store opex % (rows)
A7: Store Opex % \ Rev Growth | B7: 0 | C7: 0.02 | D7: 0.04 | E7: 0.06 | F7: 0.08
A8: 0.43 | B8: =(('Income Statement'!$C$5*(1+B$7)^3)*(1-Assumptions!$E$7-$A8-Assumptions!$E$9-Assumptions!$E$10-Assumptions!$E$11)-'Income Statement'!$C$17)*(1-Assumptions!$E$12)+('Income Statement'!$C$5*(1+B$7)^3)*Assumptions!$E$11-('Income Statement'!$C$5*(1+B$7)^3)*Assumptions!$E$15 -> 3002.2258 | C8: =(('Income Statement'!$C$5*(1+C$7)^3)*(1-Assumptions!$E$7-$A8-Assumptions!$E$9-Assumptions!$E$10-Assumptions!$E$11)-'Income Statement'!$C$17)*(1-Assumptions!$E$12)+('Income Statement'!$C$5*(1+C$7)^3)*Assumptions!$E$11-('Income Statement'!$C$5*(1+C$7)^3)*Assumptions!$E$15 -> 3205.5621 | D8: =(('Income Statement'!$C$5*(1+D$7)^3)*(1-Assumptions!$E$7-$A8-Assumptions!$E$9-Assumptions!$E$10-Assumptions!$E$11)-'Income Statement'!$C$17)*(1-Assumptions!$E$12)+('Income Statement'!$C$5*(1+D$7)^3)*Assumptions!$E$11-('Income Statement'!$C$5*(1+D$7)^3)*Assumptions!$E$15 -> 3417.0308 | E8: =(('Income Statement'!$C$5*(1+E$7)^3)*(1-Assumptions!$E$7-$A8-Assumptions!$E$9-Assumptions!$E$10-Assumptions!$E$11)-'Income Statement'!$C$17)*(1-Assumptions!$E$12)+('Income Statement'!$C$5*(1+E$7)^3)*Assumptions!$E$11-('Income Statement'!$C$5*(1+E$7)^3)*Assumptions!$E$15 -> 3636.7913 | F8: =(('Income Statement'!$C$5*(1+F$7)^3)*(1-Assumptions!$E$7-$A8-Assumptions!$E$9-Assumptions!$E$10-Assumptions!$E$11)-'Income Statement'!$C$17)*(1-Assumptions!$E$12)+('Income Statement'!$C$5*(1+F$7)^3)*Assumptions!$E$11-('Income Statement'!$C$5*(1+F$7)^3)*Assumptions!$E$15 -> 3865.0032
A9: 0.44 | B9: =(('Income Statement'!$C$5*(1+B$7)^3)*(1-Assumptions!$E$7-$A9-Assumptions!$E$9-Assumptions!$E$10-Assumptions!$E$11)-'Income Statement'!$C$17)*(1-Assumptions!$E$12)+('Income Statement'!$C$5*(1+B$7)^3)*Assumptions!$E$11-('Income Statement'!$C$5*(1+B$7)^3)*Assumptions!$E$15 -> 2725.202 | C9: =(('Income Statement'!$C$5*(1+C$7)^3)*(1-Assumptions!$E$7-$A9-Assumptions!$E$9-Assumptions!$E$10-Assumptions!$E$11)-'Income Statement'!$C$17)*(1-Assumptions!$E$12)+('Income Statement'!$C$5*(1+C$7)^3)*Assumptions!$E$11-('Income Statement'!$C$5*(1+C$7)^3)*Assumptions!$E$15 -> 2911.5822 | D9: =(('Income Statement'!$C$5*(1+D$7)^3)*(1-Assumptions!$E$7-$A9-Assumptions!$E$9-Assumptions!$E$10-Assumptions!$E$11)-'Income Statement'!$C$17)*(1-Assumptions!$E$12)+('Income Statement'!$C$5*(1+D$7)^3)*Assumptions!$E$11-('Income Statement'!$C$5*(1+D$7)^3)*Assumptions!$E$15 -> 3105.4167 | E9: =(('Income Statement'!$C$5*(1+E$7)^3)*(1-Assumptions!$E$7-$A9-Assumptions!$E$9-Assumptions!$E$10-Assumptions!$E$11)-'Income Statement'!$C$17)*(1-Assumptions!$E$12)+('Income Statement'!$C$5*(1+E$7)^3)*Assumptions!$E$11-('Income Statement'!$C$5*(1+E$7)^3)*Assumptions!$E$15 -> 3306.8516 | F9: =(('Income Statement'!$C$5*(1+F$7)^3)*(1-Assumptions!$E$7-$A9-Assumptions!$E$9-Assumptions!$E$10-Assumptions!$E$11)-'Income Statement'!$C$17)*(1-Assumptions!$E$12)+('Income Statement'!$C$5*(1+F$7)^3)*Assumptions!$E$11-('Income Statement'!$C$5*(1+F$7)^3)*Assumptions!$E$15 -> 3516.033
A10: 0.45 | B10: =(('Income Statement'!$C$5*(1+B$7)^3)*(1-Assumptions!$E$7-$A10-Assumptions!$E$9-Assumptions!$E$10-Assumptions!$E$11)-'Income Statement'!$C$17)*(1-Assumptions!$E$12)+('Income Statement'!$C$5*(1+B$7)^3)*Assumptions!$E$11-('Income Statement'!$C$5*(1+B$7)^3)*Assumptions!$E$15 -> 2448.1782 | C10: =(('Income Statement'!$C$5*(1+C$7)^3)*(1-Assumptions!$E$7-$A10-Assumptions!$E$9-Assumptions!$E$10-Assumptions!$E$11)-'Income Statement'!$C$17)*(1-Assumptions!$E$12)+('Income Statement'!$C$5*(1+C$7)^3)*Assumptions!$E$11-('Income Statement'!$C$5*(1+C$7)^3)*Assumptions!$E$15 -> 2617.6024 | D10: =(('Income Statement'!$C$5*(1+D$7)^3)*(1-Assumptions!$E$7-$A10-Assumptions!$E$9-Assumptions!$E$10-Assumptions!$E$11)-'Income Statement'!$C$17)*(1-Assumptions!$E$12)+('Income Statement'!$C$5*(1+D$7)^3)*Assumptions!$E$11-('Income Statement'!$C$5*(1+D$7)^3)*Assumptions!$E$15 -> 2793.8026 | E10: =(('Income Statement'!$C$5*(1+E$7)^3)*(1-Assumptions!$E$7-$A10-Assumptions!$E$9-Assumptions!$E$10-Assumptions!$E$11)-'Income Statement'!$C$17)*(1-Assumptions!$E$12)+('Income Statement'!$C$5*(1+E$7)^3)*Assumptions!$E$11-('Income Statement'!$C$5*(1+E$7)^3)*Assumptions!$E$15 -> 2976.9118 | F10: =(('Income Statement'!$C$5*(1+F$7)^3)*(1-Assumptions!$E$7-$A10-Assumptions!$E$9-Assumptions!$E$10-Assumptions!$E$11)-'Income Statement'!$C$17)*(1-Assumptions!$E$12)+('Income Statement'!$C$5*(1+F$7)^3)*Assumptions!$E$11-('Income Statement'!$C$5*(1+F$7)^3)*Assumptions!$E$15 -> 3167.0628
A11: 0.46 | B11: =(('Income Statement'!$C$5*(1+B$7)^3)*(1-Assumptions!$E$7-$A11-Assumptions!$E$9-Assumptions!$E$10-Assumptions!$E$11)-'Income Statement'!$C$17)*(1-Assumptions!$E$12)+('Income Statement'!$C$5*(1+B$7)^3)*Assumptions!$E$11-('Income Statement'!$C$5*(1+B$7)^3)*Assumptions!$E$15 -> 2171.1545 | C11: =(('Income Statement'!$C$5*(1+C$7)^3)*(1-Assumptions!$E$7-$A11-Assumptions!$E$9-Assumptions!$E$10-Assumptions!$E$11)-'Income Statement'!$C$17)*(1-Assumptions!$E$12)+('Income Statement'!$C$5*(1+C$7)^3)*Assumptions!$E$11-('Income Statement'!$C$5*(1+C$7)^3)*Assumptions!$E$15 -> 2323.6225 | D11: =(('Income Statement'!$C$5*(1+D$7)^3)*(1-Assumptions!$E$7-$A11-Assumptions!$E$9-Assumptions!$E$10-Assumptions!$E$11)-'Income Statement'!$C$17)*(1-Assumptions!$E$12)+('Income Statement'!$C$5*(1+D$7)^3)*Assumptions!$E$11-('Income Statement'!$C$5*(1+D$7)^3)*Assumptions!$E$15 -> 2482.1886 | E11: =(('Income Statement'!$C$5*(1+E$7)^3)*(1-Assumptions!$E$7-$A11-Assumptions!$E$9-Assumptions!$E$10-Assumptions!$E$11)-'Income Statement'!$C$17)*(1-Assumptions!$E$12)+('Income Statement'!$C$5*(1+E$7)^3)*Assumptions!$E$11-('Income Statement'!$C$5*(1+E$7)^3)*Assumptions!$E$15 -> 2646.9721 | F11: =(('Income Statement'!$C$5*(1+F$7)^3)*(1-Assumptions!$E$7-$A11-Assumptions!$E$9-Assumptions!$E$10-Assumptions!$E$11)-'Income Statement'!$C$17)*(1-Assumptions!$E$12)+('Income Statement'!$C$5*(1+F$7)^3)*Assumptions!$E$11-('Income Statement'!$C$5*(1+F$7)^3)*Assumptions!$E$15 -> 2818.0926
A12: 0.47 | B12: =(('Income Statement'!$C$5*(1+B$7)^3)*(1-Assumptions!$E$7-$A12-Assumptions!$E$9-Assumptions!$E$10-Assumptions!$E$11)-'Income Statement'!$C$17)*(1-Assumptions!$E$12)+('Income Statement'!$C$5*(1+B$7)^3)*Assumptions!$E$11-('Income Statement'!$C$5*(1+B$7)^3)*Assumptions!$E$15 -> 1894.1307 | C12: =(('Income Statement'!$C$5*(1+C$7)^3)*(1-Assumptions!$E$7-$A12-Assumptions!$E$9-Assumptions!$E$10-Assumptions!$E$11)-'Income Statement'!$C$17)*(1-Assumptions!$E$12)+('Income Statement'!$C$5*(1+C$7)^3)*Assumptions!$E$11-('Income Statement'!$C$5*(1+C$7)^3)*Assumptions!$E$15 -> 2029.6427 | D12: =(('Income Statement'!$C$5*(1+D$7)^3)*(1-Assumptions!$E$7-$A12-Assumptions!$E$9-Assumptions!$E$10-Assumptions!$E$11)-'Income Statement'!$C$17)*(1-Assumptions!$E$12)+('Income Statement'!$C$5*(1+D$7)^3)*Assumptions!$E$11-('Income Statement'!$C$5*(1+D$7)^3)*Assumptions!$E$15 -> 2170.5745 | E12: =(('Income Statement'!$C$5*(1+E$7)^3)*(1-Assumptions!$E$7-$A12-Assumptions!$E$9-Assumptions!$E$10-Assumptions!$E$11)-'Income Statement'!$C$17)*(1-Assumptions!$E$12)+('Income Statement'!$C$5*(1+E$7)^3)*Assumptions!$E$11-('Income Statement'!$C$5*(1+E$7)^3)*Assumptions!$E$15 -> 2317.0323 | F12: =(('Income Statement'!$C$5*(1+F$7)^3)*(1-Assumptions!$E$7-$A12-Assumptions!$E$9-Assumptions!$E$10-Assumptions!$E$11)-'Income Statement'!$C$17)*(1-Assumptions!$E$12)+('Income Statement'!$C$5*(1+F$7)^3)*Assumptions!$E$11-('Income Statement'!$C$5*(1+F$7)^3)*Assumptions!$E$15 -> 2469.1224
A14: Highlighted cell approximates the base-case scenario (store opex ~45.5%, growth ~4.0% avg) for reference.

Sheet Dashboard
A1: STARBUCKS — FORECAST SUMMARY DASHBOARD
A3: Line Item | B3: FY2024A | C3: FY2025A | D3: FY2026E | E3: FY2027E | F3: FY2028E
A4: Total net revenues | B4: ='Income Statement'!B5 -> 36176.2 | C4: ='Income Statement'!C5 -> 37184.4 | D4: ='Income Statement'!D5 -> 38299.932 | E4: ='Income Statement'!E5 -> 40023.429 | F4: ='Income Statement'!F5 -> 42224.718
A5: Revenue growth % | B5: ='Income Statement'!B6 -> 0 | C5: ='Income Statement'!C6 -> 0.027869152 | D5: ='Income Statement'!D6 -> 0.03 | E5: ='Income Statement'!E6 -> 0.045 | F5: ='Income Statement'!F6 -> 0.055
A6: Operating income (EBIT) | B6: ='Income Statement'!B15 -> 5408.8 | C6: ='Income Statement'!C15 -> 2936.6 | D6: ='Income Statement'!D15 -> 4116.0931 | E6: ='Income Statement'!E15 -> 4690.4006 | F6: ='Income Statement'!F15 -> 5399.2155
A7: Operating margin % | B7: ='Income Statement'!B16 -> 0.14951266 | C7: ='Income Statement'!C16 -> 0.078973978 | D7: ='Income Statement'!D16 -> 0.10746999 | E7: ='Income Statement'!E16 -> 0.11719137 | F7: ='Income Statement'!F16 -> 0.1278686
A8: Net income | B8: ='Income Statement'!B20 -> 3762.3 | C8: ='Income Statement'!C20 -> 1856.7 | D8: ='Income Statement'!D20 -> 2731.1691 | E8: ='Income Statement'!E20 -> 3148.5981 | F8: ='Income Statement'!F20 -> 3676.6652
A9: Free cash flow | B9: ='Cash Flow & Balance'!B12 -> 3762 | C9: ='Cash Flow & Balance'!C12 -> 2442 | D9: ='Cash Flow & Balance'!D12 -> 2158.3729 | E9: ='Cash Flow & Balance'!E12 -> 2594.2066 | F9: ='Cash Flow & Balance'!F12 -> 3201.9874
A10: Ending cash balance | B10: ='Cash Flow & Balance'!B18 -> 0 | C10: ='Cash Flow & Balance'!C18 -> 3219.8 | D10: ='Cash Flow & Balance'!D18 -> 2912.7749 | E10: ='Cash Flow & Balance'!E18 -> 2334.0057 | F10: ='Cash Flow & Balance'!F18 -> 2140.9089
A11: Ending total debt | B11: ='Cash Flow & Balance'!B30 -> 0 | C11: ='Cash Flow & Balance'!C30 -> 16074.8 | D11: ='Cash Flow & Balance'!D30 -> 16574.8 | E11: ='Cash Flow & Balance'!E30 -> 16574.8 | F11: ='Cash Flow & Balance'!F30 -> 16574.8
